{
  "2025-05-10T21:00:00": {
    "shortwave_radiation": 16.5,
    "wind_speed_120m": 16.5,
    "wind_speed_80m": 16.5
  },
  "2025-05-10T22:00:00": {
    "shortwave_radiation": 15.5,
    "wind_speed_120m": 15.5,
    "wind_speed_80m": 15.5
  },
  "2025-05-10T23:00:00": {
    "shortwave_radiation": 10.8,
    "wind_speed_120m": 10.8,
    "wind_speed_80m": 10.8
  },
  "2025-05-11T00:00:00": {
    "shortwave_radiation": 12.9,
    "wind_speed_120m": 12.9,
    "wind_speed_80m": 12.9
  },
  "2025-05-11T01:00:00": {
    "shortwave_radiation": 11.7,
    "wind_speed_120m": 11.7,
    "wind_speed_80m": 11.7
  },
  "2025-05-11T02:00:00": {
    "shortwave_radiation": 11.5,
    "wind_speed_120m": 11.5,
    "wind_speed_80m": 11.5
  },
  "2025-05-11T03:00:00": {
    "shortwave_radiation": 11.2,
    "wind_speed_120m": 11.2,
    "wind_speed_80m": 11.2
  },
  "2025-05-11T04:00:00": {
    "shortwave_radiation": 11.8,
    "wind_speed_120m": 11.8,
    "wind_speed_80m": 11.8
  },
  "2025-05-11T05:00:00": {
    "shortwave_radiation": 11.9,
    "wind_speed_120m": 11.9,
    "wind_speed_80m": 11.9
  },
  "2025-05-11T06:00:00": {
    "shortwave_radiation": 12.6,
    "wind_speed_120m": 12.6,
    "wind_speed_80m": 12.6
  },
  "2025-05-11T07:00:00": {
    "shortwave_radiation": 12.3,
    "wind_speed_120m": 12.3,
    "wind_speed_80m": 12.3
  },
  "2025-05-11T08:00:00": {
    "shortwave_radiation": 11.2,
    "wind_speed_120m": 11.2,
    "wind_speed_80m": 11.2
  },
  "2025-05-11T09:00:00": {
    "shortwave_radiation": 10.4,
    "wind_speed_120m": 10.4,
    "wind_speed_80m": 10.4
  },
  "2025-05-11T10:00:00": {
    "shortwave_radiation": 13.4,
    "wind_speed_120m": 13.4,
    "wind_speed_80m": 13.4
  },
  "2025-05-11T11:00:00": {
    "shortwave_radiation": 18.1,
    "wind_speed_120m": 18.1,
    "wind_speed_80m": 18.1
  },
  "2025-05-11T12:00:00": {
    "shortwave_radiation": 19.2,
    "wind_speed_120m": 19.2,
    "wind_speed_80m": 19.2
  },
  "2025-05-11T13:00:00": {
    "shortwave_radiation": 20.6,
    "wind_speed_120m": 20.6,
    "wind_speed_80m": 20.6
  },
  "2025-05-11T14:00:00": {
    "shortwave_radiation": 22.3,
    "wind_speed_120m": 22.3,
    "wind_speed_80m": 22.3
  },
  "2025-05-11T15:00:00": {
    "shortwave_radiation": 23.3,
    "wind_speed_120m": 23.3,
    "wind_speed_80m": 23.3
  },
  "2025-05-11T16:00:00": {
    "shortwave_radiation": 24.0,
    "wind_speed_120m": 24.0,
    "wind_speed_80m": 24.0
  },
  "2025-05-11T17:00:00": {
    "shortwave_radiation": 21.3,
    "wind_speed_120m": 21.3,
    "wind_speed_80m": 21.3
  },
  "2025-05-11T18:00:00": {
    "shortwave_radiation": 17.5,
    "wind_speed_120m": 17.5,
    "wind_speed_80m": 17.5
  },
  "2025-05-11T19:00:00": {
    "shortwave_radiation": 19.2,
    "wind_speed_120m": 19.2,
    "wind_speed_80m": 19.2
  },
  "2025-05-11T20:00:00": {
    "shortwave_radiation": 18.6,
    "wind_speed_120m": 18.6,
    "wind_speed_80m": 18.6
  },
  "2025-05-11T21:00:00": {
    "shortwave_radiation": 15.5,
    "wind_speed_120m": 15.5,
    "wind_speed_80m": 15.5
  }
}